cupy_xarray/__init__.py
cupy_xarray/_version.py
cupy_xarray/accessors.py
cupy_xarray/tests/test_accessors.py
cupy_xarray-0.1.4.dist-info/LICENSE
cupy_xarray-0.1.4.dist-info/METADATA
cupy_xarray-0.1.4.dist-info/WHEEL
cupy_xarray-0.1.4.dist-info/top_level.txt
cupy_xarray-0.1.4.dist-info/RECORD
