Metadata-Version: 2.1
Name: cupy-xarray
Version: 0.1.4
Summary: Interface for using cupy in xarray, providing convenience accessors.
Author: cupy-xarray developers
License: Apache License
Classifier: Programming Language :: Python :: 3
Classifier: Operating System :: OS Independent
Requires-Python: >=3.8
License-File: LICENSE
Requires-Dist: cupy
Requires-Dist: xarray >=2024.02.0
Provides-Extra: test
Requires-Dist: dask ; extra == 'test'
Requires-Dist: pytest ; extra == 'test'
